deezspot/__init__.py
deezspot/easy_spoty.py
deezspot/exceptions.py
deezspot/deezloader/__dee_api__.py
deezspot/deezloader/__download__.py
deezspot/deezloader/__download_utils__.py
deezspot/deezloader/__init__.py
deezspot/deezloader/__utils__.py
deezspot/deezloader/dee_api.py
deezspot/deezloader/deegw_api.py
deezspot/deezloader/deezer_settings.py
deezspot/libutils/__init__.py
deezspot/libutils/audio_converter.py
deezspot/libutils/cleanup_utils.py
deezspot/libutils/librespot.py
deezspot/libutils/logging_utils.py
deezspot/libutils/metadata_converter.py
deezspot/libutils/others_settings.py
deezspot/libutils/progress_reporter.py
deezspot/libutils/skip_detection.py
deezspot/libutils/taggers.py
deezspot/libutils/utils.py
deezspot/libutils/write_m3u.py
deezspot/libutils/write_tags.py
deezspot/models/__init__.py
deezspot/models/callback/__init__.py
deezspot/models/callback/album.py
deezspot/models/callback/artist.py
deezspot/models/callback/callbacks.py
deezspot/models/callback/common.py
deezspot/models/callback/playlist.py
deezspot/models/callback/track.py
deezspot/models/callback/user.py
deezspot/models/download/__init__.py
deezspot/models/download/album.py
deezspot/models/download/episode.py
deezspot/models/download/playlist.py
deezspot/models/download/preferences.py
deezspot/models/download/smart.py
deezspot/models/download/track.py
deezspot/models/librespot/__init__.py
deezspot/models/librespot/album.py
deezspot/models/librespot/artist.py
deezspot/models/librespot/playlist.py
deezspot/models/librespot/track.py
deezspot/models/librespot/types.py
deezspot/spotloader/__download__.py
deezspot/spotloader/__init__.py
deezspot/spotloader/__spo_api__.py
deezspot/spotloader/spotify_settings.py
deezspot_spotizerr_phoenix-0.0.14.dist-info/licenses/LICENSE
deezspot_spotizerr_phoenix-0.0.14.dist-info/METADATA
deezspot_spotizerr_phoenix-0.0.14.dist-info/WHEEL
deezspot_spotizerr_phoenix-0.0.14.dist-info/top_level.txt
deezspot_spotizerr_phoenix-0.0.14.dist-info/RECORD
