Metadata-Version: 2.4
Name: deezspot-spotizerr-phoenix
Version: 0.0.14
Summary: Downloads songs, albums or playlists from deezer and spotify (clone from deezloader)
Home-page: https://lavaforge.org/spotizerrphoenix/deezspot-spotizerr-phoenix
Author: spotizerr-phoenix
Author-email: spotizerr-phoenix <spotizerrphoenix@proton.me>
License: GNU Affero General Public License v3
Project-URL: Homepage, https://lavaforge.org/spotizerrphoenix/deezspot-spotizerr-phoenix
Project-URL: Repository, https://lavaforge.org/spotizerrphoenix/deezspot-spotizerr-phoenix.git
Project-URL: Documentation, https://lavaforge.org/spotizerrphoenix/deezspot-spotizerr-phoenix/src/branch/main/README.md
Requires-Python: >=3.10
License-File: LICENSE
Requires-Dist: mutagen==1.47.0
Requires-Dist: pycryptodome==3.23.0
Requires-Dist: requests==2.32.3
Requires-Dist: tqdm==4.67.1
Requires-Dist: fastapi==0.116.1
Requires-Dist: uvicorn[standard]==0.35.0
Requires-Dist: librespot-spotizerr-phoenix
Requires-Dist: rapidfuzz==3.13.0
Requires-Dist: spotipy==2.25.1
Dynamic: author
Dynamic: home-page
Dynamic: license-file
Dynamic: requires-python
